LICENSE
README.md
pyproject.toml
setup.cfg
setup.py
logprocessor/__init__.py
logprocessor/cli.py
logprocessor/plugin.py
logprocessor/plugin.pyi
logprocessor/process.py
logprocessor/py.typed
logprocessor.egg-info/PKG-INFO
logprocessor.egg-info/SOURCES.txt
logprocessor.egg-info/dependency_links.txt
logprocessor.egg-info/entry_points.txt
logprocessor.egg-info/requires.txt
logprocessor.egg-info/top_level.txt
logprocessor/libs/fast_metric_merge.c
logprocessor/libs/fast_metric_merge.pyi
logprocessor/metrics/__init__.py
logprocessor/metrics/bare_metrics.py
logprocessor/metrics/bare_metrics.pyi
logprocessor/metrics/base_metrics.py
logprocessor/metrics/base_metrics.pyi
logprocessor/metrics/wisp_metrics.py
logprocessor/metrics/wisp_metrics.pyi
tests/test_fast_merge.py
tests/test_logmetrics.py
tests/test_logmetricstransformer.py